chester/__init__.py
chester/add_variants.py
chester/auto_pull.py
chester/availability_test.py
chester/config.py
chester/config_ec2.py
chester/hydra_utils.py
chester/logger.py
chester/pull_result.py
chester/pull_s3_result.py
chester/rsync_exclude
chester/rsync_include
chester/run_exp.py
chester/run_exp_worker.py
chester/setup_ec2_for_chester.py
chester/slurm.py
chester/utils_logger.py
chester/utils_s3.py
chester/scheduler/__init__.py
chester/scheduler/kill_all_jobs.py
chester/scheduler/list_jobs.py
chester/scheduler/remote_scheduler.py
chester/scheduler/remote_slurm_launcher.py
chester_ml-0.2.1.dist-info/METADATA
chester_ml-0.2.1.dist-info/WHEEL
chester_ml-0.2.1.dist-info/entry_points.txt
chester_ml-0.2.1.dist-info/top_level.txt
chester_ml-0.2.1.dist-info/RECORD
